[
  {
    "Type": "DataTable",
    "Name": "DT_Story_01_Chapter_12_Talk",
    "Class": "UScriptClass'DataTable'",
    "Flags": "RF_Public | RF_Standalone | RF_Transactional | RF_WasLoaded | RF_LoadCompleted",
    "Properties": {
      "RowStruct": {
        "ObjectName": "ScriptStruct'StoryRaceTalkData_Message'",
        "ObjectPath": "/Script/GameProject"
      }
    },
    "Rows": {
      "SRT_1_10_1-01": {
        "EpisodeID": 55,
        "CharacterID": "TOKYO_S15",
        "FaceImageNo": 0,
        "Message": {
          "TableId": "/Game/IND/StringTable/Story/Racetext/Storytype1/story_RT_1_10.story_RT_1_10",
          "Key": "1_10_1-01",
          "SourceString": "Somehow, I ended up in the\r\nmiddle of a battle but‥",
          "LocalizedString": "Somehow, I ended up in the\r\nmiddle of a battle but‥"
        },
        "DrawTime": 3.0,
        "Condition": {
          "Type": "EStoryRaceTalk_ConditionType::PlayerProgress",
          "ProgressRate": 0.001,
          "ProgressRateEnd": -1.0,
          "Rival": 0,
          "Advantage": 0.0
        }
      },
      "SRT_1_10_1-02": {
        "EpisodeID": 55,
        "CharacterID": "TOKYO_S15",
        "FaceImageNo": 0,
        "Message": {
          "TableId": "/Game/IND/StringTable/Story/Racetext/Storytype1/story_RT_1_10.story_RT_1_10",
          "Key": "1_10_1-02",
          "SourceString": "I can't forgive myself for\r\ninterrupting their conversation‥",
          "LocalizedString": "I can't forgive myself for\r\ninterrupting their conversation‥"
        },
        "DrawTime": 2.5,
        "Condition": {
          "Type": "EStoryRaceTalk_ConditionType::PlayerProgress",
          "ProgressRate": 0.02,
          "ProgressRateEnd": -1.0,
          "Rival": 0,
          "Advantage": 0.0
        }
      },
      "SRT_1_10_1-03": {
        "EpisodeID": 55,
        "CharacterID": "TOKYO_S15",
        "FaceImageNo": 0,
        "Message": {
          "TableId": "/Game/IND/StringTable/Story/Racetext/Storytype1/story_RT_1_10.story_RT_1_10",
          "Key": "1_10_1-03",
          "SourceString": "Can you beat me trained at\r\nthe circuit driving event‥?",
          "LocalizedString": "Can you beat me trained at\r\nthe circuit driving event‥?"
        },
        "DrawTime": 2.5,
        "Condition": {
          "Type": "EStoryRaceTalk_ConditionType::PlayerProgress",
          "ProgressRate": 0.04,
          "ProgressRateEnd": -1.0,
          "Rival": 0,
          "Advantage": 0.0
        }
      },
      "SRT_1_10_1-04": {
        "EpisodeID": 55,
        "CharacterID": "TOKYO_GLASSES",
        "FaceImageNo": 0,
        "Message": {
          "TableId": "/Game/IND/StringTable/Story/Racetext/Storytype1/story_RT_1_10.story_RT_1_10",
          "Key": "1_10_1-04",
          "SourceString": "You're faster than I thought‥\r\nEven the local street racers‥",
          "LocalizedString": "You're faster than I thought‥\r\nEven the local street racers‥"
        },
        "DrawTime": 3.0,
        "Condition": {
          "Type": "EStoryRaceTalk_ConditionType::PlayerProgress",
          "ProgressRate": 0.145,
          "ProgressRateEnd": -1.0,
          "Rival": 0,
          "Advantage": 0.0
        }
      },
      "SRT_1_10_1-05": {
        "EpisodeID": 55,
        "CharacterID": "TOKYO_S15",
        "FaceImageNo": 0,
        "Message": {
          "TableId": "/Game/IND/StringTable/Story/Racetext/Storytype1/story_RT_1_10.story_RT_1_10",
          "Key": "1_10_1-05",
          "SourceString": "Well, you're\r\nmaking quite the comeback‥",
          "LocalizedString": "Well, you're\r\nmaking quite the comeback‥"
        },
        "DrawTime": 3.0,
        "Condition": {
          "Type": "EStoryRaceTalk_ConditionType::PlayerProgress",
          "ProgressRate": 0.165,
          "ProgressRateEnd": -1.0,
          "Rival": 0,
          "Advantage": 0.0
        }
      },
      "SRT_1_10_1-06": {
        "EpisodeID": 55,
        "CharacterID": "TOKYO_S15",
        "FaceImageNo": 0,
        "Message": {
          "TableId": "/Game/IND/StringTable/Story/Racetext/Storytype1/story_RT_1_10.story_RT_1_10",
          "Key": "1_10_1-06",
          "SourceString": "But I can keep up\r\nwith you easily‥",
          "LocalizedString": "But I can keep up\r\nwith you easily‥"
        },
        "DrawTime": 3.0,
        "Condition": {
          "Type": "EStoryRaceTalk_ConditionType::PlayerProgress",
          "ProgressRate": 0.185,
          "ProgressRateEnd": -1.0,
          "Rival": 0,
          "Advantage": 0.0
        }
      },
      "SRT_1_10_1-07": {
        "EpisodeID": 55,
        "CharacterID": "TOKYO_S15",
        "FaceImageNo": 0,
        "Message": {
          "TableId": "/Game/IND/StringTable/Story/Racetext/Storytype1/story_RT_1_10.story_RT_1_10",
          "Key": "1_10_1-07",
          "SourceString": "I've gained\r\nconfidence in my skills",
          "LocalizedString": "I've gained\r\nconfidence in my skills"
        },
        "DrawTime": 3.0,
        "Condition": {
          "Type": "EStoryRaceTalk_ConditionType::PlayerProgress",
          "ProgressRate": 0.205,
          "ProgressRateEnd": -1.0,
          "Rival": 0,
          "Advantage": 0.0
        }
      },
      "SRT_1_10_1-08": {
        "EpisodeID": 55,
        "CharacterID": "TOKYO_S15",
        "FaceImageNo": 0,
        "Message": {
          "TableId": "/Game/IND/StringTable/Story/Racetext/Storytype1/story_RT_1_10.story_RT_1_10",
          "Key": "1_10_1-08",
          "SourceString": "I'm really fast, huh‥",
          "LocalizedString": "I'm really fast, huh‥"
        },
        "DrawTime": 3.0,
        "Condition": {
          "Type": "EStoryRaceTalk_ConditionType::PlayerProgress",
          "ProgressRate": 0.225,
          "ProgressRateEnd": -1.0,
          "Rival": 0,
          "Advantage": 0.0
        }
      },
      "SRT_1_10_1-09": {
        "EpisodeID": 55,
        "CharacterID": "TOKYO_S15",
        "FaceImageNo": 0,
        "Message": {
          "TableId": "/Game/IND/StringTable/Story/Racetext/Storytype1/story_RT_1_10.story_RT_1_10",
          "Key": "1_10_1-09",
          "SourceString": "I might be pretty cool‥",
          "LocalizedString": "I might be pretty cool‥"
        },
        "DrawTime": 2.0,
        "Condition": {
          "Type": "EStoryRaceTalk_ConditionType::PlayerProgress",
          "ProgressRate": 0.245,
          "ProgressRateEnd": -1.0,
          "Rival": 0,
          "Advantage": 0.0
        }
      },
      "SRT_1_10_1-10": {
        "EpisodeID": 55,
        "CharacterID": "TOKYO_S15",
        "FaceImageNo": 0,
        "Message": {
          "TableId": "/Game/IND/StringTable/Story/Racetext/Storytype1/story_RT_1_10.story_RT_1_10",
          "Key": "1_10_1-10",
          "SourceString": "Can you keep up!!\r\nFull circuit braking!!",
          "LocalizedString": "Can you keep up!!\r\nFull circuit braking!!"
        },
        "DrawTime": 3.0,
        "Condition": {
          "Type": "EStoryRaceTalk_ConditionType::PlayerProgress",
          "ProgressRate": 0.295,
          "ProgressRateEnd": -1.0,
          "Rival": 0,
          "Advantage": 0.0
        }
      },
      "SRT_1_10_1-11": {
        "EpisodeID": 55,
        "CharacterID": "TOKYO_S15",
        "FaceImageNo": 0,
        "Message": {
          "TableId": "/Game/IND/StringTable/Story/Racetext/Storytype1/story_RT_1_10.story_RT_1_10",
          "Key": "1_10_1-11",
          "SourceString": "Phew‥ My heart\r\nwas pounding like crazy",
          "LocalizedString": "Phew‥ My heart\r\nwas pounding like crazy"
        },
        "DrawTime": 3.0,
        "Condition": {
          "Type": "EStoryRaceTalk_ConditionType::PlayerProgress",
          "ProgressRate": 0.325,
          "ProgressRateEnd": -1.0,
          "Rival": 0,
          "Advantage": 0.0
        }
      },
      "SRT_1_10_1-12": {
        "EpisodeID": 55,
        "CharacterID": "TOKYO_S15",
        "FaceImageNo": 0,
        "Message": {
          "TableId": "/Game/IND/StringTable/Story/Racetext/Storytype1/story_RT_1_10.story_RT_1_10",
          "Key": "1_10_1-12",
          "SourceString": "What's going on?\r\nThere's no way you can keep up‥ Huh‥？",
          "LocalizedString": "What's going on?\r\nThere's no way you can keep up‥ Huh‥？"
        },
        "DrawTime": 2.0,
        "Condition": {
          "Type": "EStoryRaceTalk_ConditionType::PlayerProgress",
          "ProgressRate": 0.36,
          "ProgressRateEnd": -1.0,
          "Rival": 0,
          "Advantage": 0.0
        }
      },
      "SRT_1_10_1-13": {
        "EpisodeID": 55,
        "CharacterID": "TOKYO_GLASSES",
        "FaceImageNo": 1,
        "Message": {
          "TableId": "/Game/IND/StringTable/Story/Racetext/Storytype1/story_RT_1_10.story_RT_1_10",
          "Key": "1_10_1-13",
          "SourceString": "Whoa!! You're right behind me‥\r\nWhat's happening？",
          "LocalizedString": "Whoa!! You're right behind me‥\r\nWhat's happening？"
        },
        "DrawTime": 3.0,
        "Condition": {
          "Type": "EStoryRaceTalk_ConditionType::PlayerProgress",
          "ProgressRate": 0.38,
          "ProgressRateEnd": -1.0,
          "Rival": 0,
          "Advantage": 0.0
        }
      },
      "SRT_1_10_1-14": {
        "EpisodeID": 55,
        "CharacterID": "TOKYO_S15",
        "FaceImageNo": 1,
        "Message": {
          "TableId": "/Game/IND/StringTable/Story/Racetext/Storytype1/story_RT_1_10.story_RT_1_10",
          "Key": "1_10_1-14",
          "SourceString": "Don't be stupid‥ If you think\r\nyou can follow me, you are wrong",
          "LocalizedString": "Don't be stupid‥ If you think\r\nyou can follow me, you are wrong"
        },
        "DrawTime": 3.0,
        "Condition": {
          "Type": "EStoryRaceTalk_ConditionType::PlayerProgress",
          "ProgressRate": 0.4,
          "ProgressRateEnd": -1.0,
          "Rival": 0,
          "Advantage": 0.0
        }
      },
      "SRT_1_10_1-15": {
        "EpisodeID": 55,
        "CharacterID": "TOKYO_S15",
        "FaceImageNo": 1,
        "Message": {
          "TableId": "/Game/IND/StringTable/Story/Racetext/Storytype1/story_RT_1_10.story_RT_1_10",
          "Key": "1_10_1-15",
          "SourceString": "I'll shake you off in no time!!",
          "LocalizedString": "I'll shake you off in no time!!"
        },
        "DrawTime": 3.0,
        "Condition": {
          "Type": "EStoryRaceTalk_ConditionType::PlayerProgress",
          "ProgressRate": 0.42,
          "ProgressRateEnd": -1.0,
          "Rival": 0,
          "Advantage": 0.0
        }
      },
      "SRT_1_10_1-16": {
        "EpisodeID": 55,
        "CharacterID": "TOKYO_S15",
        "FaceImageNo": 0,
        "Message": {
          "TableId": "/Game/IND/StringTable/Story/Racetext/Storytype1/story_RT_1_10.story_RT_1_10",
          "Key": "1_10_1-16",
          "SourceString": "The straight ahead is my chance!!\r\nI'll break away!!",
          "LocalizedString": "The straight ahead is my chance!!\r\nI'll break away!!"
        },
        "DrawTime": 3.0,
        "Condition": {
          "Type": "EStoryRaceTalk_ConditionType::PlayerProgress",
          "ProgressRate": 0.465,
          "ProgressRateEnd": -1.0,
          "Rival": 0,
          "Advantage": 0.0
        }
      },
      "SRT_1_10_1-17": {
        "EpisodeID": 55,
        "CharacterID": "TOKYO_S15",
        "FaceImageNo": 1,
        "Message": {
          "TableId": "/Game/IND/StringTable/Story/Racetext/Storytype1/story_RT_1_10.story_RT_1_10",
          "Key": "1_10_1-17",
          "SourceString": "Huh... I thought I was out of\r\nsight, but than you're close by!?",
          "LocalizedString": "Huh... I thought I was out of\r\nsight, but than you're close by!?"
        },
        "DrawTime": 3.0,
        "Condition": {
          "Type": "EStoryRaceTalk_ConditionType::PlayerProgress",
          "ProgressRate": 0.645,
          "ProgressRateEnd": -1.0,
          "Rival": 0,
          "Advantage": 0.0
        }
      },
      "SRT_1_10_1-18": {
        "EpisodeID": 55,
        "CharacterID": "TOKYO_S15",
        "FaceImageNo": 1,
        "Message": {
          "TableId": "/Game/IND/StringTable/Story/Racetext/Storytype1/story_RT_1_10.story_RT_1_10",
          "Key": "1_10_1-18",
          "SourceString": "My braking, honed on the circuit‥\r\nlosing to a mountain pass racer‥!?",
          "LocalizedString": "My braking, honed on the circuit‥\r\nlosing to a mountain pass racer‥!?"
        },
        "DrawTime": 3.0,
        "Condition": {
          "Type": "EStoryRaceTalk_ConditionType::PlayerProgress",
          "ProgressRate": 0.665,
          "ProgressRateEnd": -1.0,
          "Rival": 0,
          "Advantage": 0.0
        }
      },
      "SRT_1_10_1-19": {
        "EpisodeID": 55,
        "CharacterID": "TOKYO_S15",
        "FaceImageNo": 1,
        "Message": {
          "TableId": "/Game/IND/StringTable/Story/Racetext/Storytype1/story_RT_1_10.story_RT_1_10",
          "Key": "1_10_1-19",
          "SourceString": "No, braking is my specialty‥\r\nIf I get serious, I won't lose‥",
          "LocalizedString": "No, braking is my specialty‥\r\nIf I get serious, I won't lose‥"
        },
        "DrawTime": 3.0,
        "Condition": {
          "Type": "EStoryRaceTalk_ConditionType::PlayerProgress",
          "ProgressRate": 0.735,
          "ProgressRateEnd": -1.0,
          "Rival": 0,
          "Advantage": 0.0
        }
      },
      "SRT_1_10_1-20": {
        "EpisodeID": 55,
        "CharacterID": "TOKYO_S15",
        "FaceImageNo": 0,
        "Message": {
          "TableId": "/Game/IND/StringTable/Story/Racetext/Storytype1/story_RT_1_10.story_RT_1_10",
          "Key": "1_10_1-20",
          "SourceString": "I'll focus 120%‥ Just like when I\r\nhit the first corner of the circuit‥",
          "LocalizedString": "I'll focus 120%‥ Just like when I\r\nhit the first corner of the circuit‥"
        },
        "DrawTime": 3.0,
        "Condition": {
          "Type": "EStoryRaceTalk_ConditionType::PlayerProgress",
          "ProgressRate": 0.765,
          "ProgressRateEnd": -1.0,
          "Rival": 0,
          "Advantage": 0.0
        }
      },
      "SRT_1_10_1-21": {
        "EpisodeID": 55,
        "CharacterID": "TOKYO_S15",
        "FaceImageNo": 0,
        "Message": {
          "TableId": "/Game/IND/StringTable/Story/Racetext/Storytype1/story_RT_1_10.story_RT_1_10",
          "Key": "1_10_1-21",
          "SourceString": "Now!! Here I go!! The ultra‥",
          "LocalizedString": "Now!! Here I go!! The ultra‥"
        },
        "DrawTime": 1.5,
        "Condition": {
          "Type": "EStoryRaceTalk_ConditionType::PlayerProgress",
          "ProgressRate": 0.785,
          "ProgressRateEnd": -1.0,
          "Rival": 0,
          "Advantage": 0.0
        }
      },
      "SRT_1_10_1-22": {
        "EpisodeID": 55,
        "CharacterID": "TOKYO_S15",
        "FaceImageNo": 1,
        "Message": {
          "TableId": "/Game/IND/StringTable/Story/Racetext/Storytype1/story_RT_1_10.story_RT_1_10",
          "Key": "1_10_1-22",
          "SourceString": "Super‥ ultra‥\r\nultra-super late braking‥",
          "LocalizedString": "Super‥ ultra‥\r\nultra-super late braking‥"
        },
        "DrawTime": 2.0,
        "Condition": {
          "Type": "EStoryRaceTalk_ConditionType::PlayerProgress",
          "ProgressRate": 0.8,
          "ProgressRateEnd": -1.0,
          "Rival": 0,
          "Advantage": 0.0
        }
      },
      "SRT_1_10_1-23": {
        "EpisodeID": 55,
        "CharacterID": "TOKYO2",
        "FaceImageNo": 1,
        "Message": {
          "TableId": "/Game/IND/StringTable/Story/Racetext/Storytype1/story_RT_1_10.story_RT_1_10",
          "Key": "1_10_1-23",
          "SourceString": "Whooooaaah",
          "LocalizedString": "Whooooaaah"
        },
        "DrawTime": 3.0,
        "Condition": {
          "Type": "EStoryRaceTalk_ConditionType::PlayerProgress",
          "ProgressRate": 0.814,
          "ProgressRateEnd": -1.0,
          "Rival": 0,
          "Advantage": 0.0
        }
      },
      "SRT_1_10_1-24": {
        "EpisodeID": 55,
        "CharacterID": "TOKYO_S15",
        "FaceImageNo": 1,
        "Message": {
          "TableId": "/Game/IND/StringTable/Story/Racetext/Storytype1/story_RT_1_10.story_RT_1_10",
          "Key": "1_10_1-24",
          "SourceString": "Hiiii... No, I'm upset",
          "LocalizedString": "Hiiii... No, I'm upset"
        },
        "DrawTime": 3.0,
        "Condition": {
          "Type": "EStoryRaceTalk_ConditionType::PlayerProgress",
          "ProgressRate": 0.825,
          "ProgressRateEnd": -1.0,
          "Rival": 0,
          "Advantage": 0.0
        }
      },
      "SRT_1_10_1-25": {
        "EpisodeID": 55,
        "CharacterID": "TOKYO_GLASSES",
        "FaceImageNo": 1,
        "Message": {
          "TableId": "/Game/IND/StringTable/Story/Racetext/Storytype1/story_RT_1_10.story_RT_1_10",
          "Key": "1_10_1-25",
          "SourceString": "Oh no, how uncool",
          "LocalizedString": "Oh no, how uncool"
        },
        "DrawTime": 3.0,
        "Condition": {
          "Type": "EStoryRaceTalk_ConditionType::PlayerProgress",
          "ProgressRate": 0.85,
          "ProgressRateEnd": -1.0,
          "Rival": 0,
          "Advantage": 0.0
        }
      },
      "SRT_1_10_2-01": {
        "EpisodeID": 56,
        "CharacterID": "SAYUKI",
        "FaceImageNo": 0,
        "Message": {
          "TableId": "/Game/IND/StringTable/Story/Racetext/Storytype1/story_RT_1_10.story_RT_1_10",
          "Key": "1_10_2-01",
          "SourceString": "Mako, you know what I mean",
          "LocalizedString": "Mako, you know what I mean"
        },
        "DrawTime": 3.0,
        "Condition": {
          "Type": "EStoryRaceTalk_ConditionType::PlayerProgress",
          "ProgressRate": 0.001,
          "ProgressRateEnd": -1.0,
          "Rival": 0,
          "Advantage": 0.0
        }
      },
      "SRT_1_10_2-02": {
        "EpisodeID": 56,
        "CharacterID": "MAKO",
        "FaceImageNo": 0,
        "Message": {
          "TableId": "/Game/IND/StringTable/Story/Racetext/Storytype1/story_RT_1_10.story_RT_1_10",
          "Key": "1_10_2-02",
          "SourceString": "Of course, I'll go full\r\nthrottle from the start‥!!",
          "LocalizedString": "Of course, I'll go full\r\nthrottle from the start‥!!"
        },
        "DrawTime": 3.0,
        "Condition": {
          "Type": "EStoryRaceTalk_ConditionType::PlayerProgress",
          "ProgressRate": 0.02,
          "ProgressRateEnd": -1.0,
          "Rival": 0,
          "Advantage": 0.0
        }
      },
      "SRT_1_10_2-03": {
        "EpisodeID": 56,
        "CharacterID": "SAYUKI",
        "FaceImageNo": 0,
        "Message": {
          "TableId": "/Game/IND/StringTable/Story/Racetext/Storytype1/story_RT_1_10.story_RT_1_10",
          "Key": "1_10_2-03",
          "SourceString": "That's the way to go!!",
          "LocalizedString": "That's the way to go!!"
        },
        "DrawTime": 3.0,
        "Condition": {
          "Type": "EStoryRaceTalk_ConditionType::PlayerProgress",
          "ProgressRate": 0.04,
          "ProgressRateEnd": -1.0,
          "Rival": 0,
          "Advantage": 0.0
        }
      },
      "SRT_1_10_2-04": {
        "EpisodeID": 56,
        "CharacterID": "SAYUKI",
        "FaceImageNo": 0,
        "Message": {
          "TableId": "/Game/IND/StringTable/Story/Racetext/Storytype1/story_RT_1_10.story_RT_1_10",
          "Key": "1_10_2-04",
          "SourceString": "Alright, let's hit them hard\r\nwith all we've got today‥!!",
          "LocalizedString": "Alright, let's hit them hard\r\nwith all we've got today‥!!"
        },
        "DrawTime": 3.0,
        "Condition": {
          "Type": "EStoryRaceTalk_ConditionType::PlayerProgress",
          "ProgressRate": 0.095,
          "ProgressRateEnd": -1.0,
          "Rival": 0,
          "Advantage": 0.0
        }
      },
      "SRT_1_10_2-05": {
        "EpisodeID": 56,
        "CharacterID": "MAKO",
        "FaceImageNo": 0,
        "Message": {
          "TableId": "/Game/IND/StringTable/Story/Racetext/Storytype1/story_RT_1_10.story_RT_1_10",
          "Key": "1_10_2-05",
          "SourceString": "OK‥!!",
          "LocalizedString": "OK‥!!"
        },
        "DrawTime": 3.0,
        "Condition": {
          "Type": "EStoryRaceTalk_ConditionType::PlayerProgress",
          "ProgressRate": 0.115,
          "ProgressRateEnd": -1.0,
          "Rival": 0,
          "Advantage": 0.0
        }
      },
      "SRT_1_10_2-06": {
        "EpisodeID": 56,
        "CharacterID": "SAYUKI",
        "FaceImageNo": 0,
        "Message": {
          "TableId": "/Game/IND/StringTable/Story/Racetext/Storytype1/story_RT_1_10.story_RT_1_10",
          "Key": "1_10_2-06",
          "SourceString": "Mako, that's great!!\r\nYou're seriously on fire!!",
          "LocalizedString": "Mako, that's great!!\r\nYou're seriously on fire!!"
        },
        "DrawTime": 3.0,
        "Condition": {
          "Type": "EStoryRaceTalk_ConditionType::PlayerProgress",
          "ProgressRate": 0.145,
          "ProgressRateEnd": -1.0,
          "Rival": 0,
          "Advantage": 0.0
        }
      },
      "SRT_1_10_2-07": {
        "EpisodeID": 56,
        "CharacterID": "SAYUKI",
        "FaceImageNo": 0,
        "Message": {
          "TableId": "/Game/IND/StringTable/Story/Racetext/Storytype1/story_RT_1_10.story_RT_1_10",
          "Key": "1_10_2-07",
          "SourceString": "Let's widen the gap even\r\nmore in the next S-curve!!",
          "LocalizedString": "Let's widen the gap even\r\nmore in the next S-curve!!"
        },
        "DrawTime": 3.0,
        "Condition": {
          "Type": "EStoryRaceTalk_ConditionType::PlayerProgress",
          "ProgressRate": 0.165,
          "ProgressRateEnd": -1.0,
          "Rival": 0,
          "Advantage": 0.0
        }
      },
      "SRT_1_10_2-08": {
        "EpisodeID": 56,
        "CharacterID": "MAKO",
        "FaceImageNo": 0,
        "Message": {
          "TableId": "/Game/IND/StringTable/Story/Racetext/Storytype1/story_RT_1_10.story_RT_1_10",
          "Key": "1_10_2-08",
          "SourceString": "Yeah‥!!",
          "LocalizedString": "Yeah‥!!"
        },
        "DrawTime": 3.0,
        "Condition": {
          "Type": "EStoryRaceTalk_ConditionType::PlayerProgress",
          "ProgressRate": 0.185,
          "ProgressRateEnd": -1.0,
          "Rival": 0,
          "Advantage": 0.0
        }
      },
      "SRT_1_10_2-09": {
        "EpisodeID": 56,
        "CharacterID": "SAYUKI",
        "FaceImageNo": 0,
        "Message": {
          "TableId": "/Game/IND/StringTable/Story/Racetext/Storytype1/story_RT_1_10.story_RT_1_10",
          "Key": "1_10_2-09",
          "SourceString": "It feels great!!\r\nLet's keep going like this!!",
          "LocalizedString": "It feels great!!\r\nLet's keep going like this!!"
        },
        "DrawTime": 3.0,
        "Condition": {
          "Type": "EStoryRaceTalk_ConditionType::PlayerProgress",
          "ProgressRate": 0.25,
          "ProgressRateEnd": -1.0,
          "Rival": 0,
          "Advantage": 0.0
        }
      },
      "SRT_1_10_2-10": {
        "EpisodeID": 56,
        "CharacterID": "SAYUKI",
        "FaceImageNo": 0,
        "Message": {
          "TableId": "/Game/IND/StringTable/Story/Racetext/Storytype1/story_RT_1_10.story_RT_1_10",
          "Key": "1_10_2-10",
          "SourceString": "We'll shake them off\r\nat the next C-121!!",
          "LocalizedString": "We'll shake them off\r\nat the next C-121!!"
        },
        "DrawTime": 3.0,
        "Condition": {
          "Type": "EStoryRaceTalk_ConditionType::PlayerProgress",
          "ProgressRate": 0.58,
          "ProgressRateEnd": -1.0,
          "Rival": 0,
          "Advantage": 0.0
        }
      },
      "SRT_1_10_2-11": {
        "EpisodeID": 56,
        "CharacterID": "MAKO",
        "FaceImageNo": 0,
        "Message": {
          "TableId": "/Game/IND/StringTable/Story/Racetext/Storytype1/story_RT_1_10.story_RT_1_10",
          "Key": "1_10_2-11",
          "SourceString": "Leave it to me‥!!",
          "LocalizedString": "Leave it to me‥!!"
        },
        "DrawTime": 3.0,
        "Condition": {
          "Type": "EStoryRaceTalk_ConditionType::PlayerProgress",
          "ProgressRate": 0.6,
          "ProgressRateEnd": -1.0,
          "Rival": 0,
          "Advantage": 0.0
        }
      },
      "SRT_1_10_2-12": {
        "EpisodeID": 56,
        "CharacterID": "MAKO",
        "FaceImageNo": 1,
        "Message": {
          "TableId": "/Game/IND/StringTable/Story/Racetext/Storytype1/story_RT_1_10.story_RT_1_10",
          "Key": "1_10_2-12",
          "SourceString": "Urgh‥!!",
          "LocalizedString": "Urgh‥!!"
        },
        "DrawTime": 1.5,
        "Condition": {
          "Type": "EStoryRaceTalk_ConditionType::PlayerProgress",
          "ProgressRate": 0.63,
          "ProgressRateEnd": -1.0,
          "Rival": 0,
          "Advantage": 0.0
        }
      },
      "SRT_1_10_2-13": {
        "EpisodeID": 56,
        "CharacterID": "SAYUKI",
        "FaceImageNo": 1,
        "Message": {
          "TableId": "/Game/IND/StringTable/Story/Racetext/Storytype1/story_RT_1_10.story_RT_1_10",
          "Key": "1_10_2-13",
          "SourceString": "Even like this, they\r\ncan't shake us off‥!!",
          "LocalizedString": "Even like this, they\r\ncan't shake us off‥!!"
        },
        "DrawTime": 3.0,
        "Condition": {
          "Type": "EStoryRaceTalk_ConditionType::PlayerProgress",
          "ProgressRate": 0.645,
          "ProgressRateEnd": -1.0,
          "Rival": 0,
          "Advantage": 0.0
        }
      },
      "SRT_1_10_2-14": {
        "EpisodeID": 56,
        "CharacterID": "MAKO&SAYUKI",
        "FaceImageNo": 1,
        "Message": {
          "TableId": "/Game/IND/StringTable/Story/Racetext/Storytype1/story_RT_1_10.story_RT_1_10",
          "Key": "1_10_2-14",
          "SourceString": "Unbelievable!!",
          "LocalizedString": "Unbelievable!!"
        },
        "DrawTime": 1.5,
        "Condition": {
          "Type": "EStoryRaceTalk_ConditionType::AdvantageOver",
          "ProgressRate": 0.725,
          "ProgressRateEnd": 0.76,
          "Rival": 0,
          "Advantage": 4.0
        }
      },
      "SRT_1_10_2-15": {
        "EpisodeID": 56,
        "CharacterID": "MAKO",
        "FaceImageNo": 0,
        "Message": {
          "TableId": "/Game/IND/StringTable/Story/Racetext/Storytype1/story_RT_1_10.story_RT_1_10",
          "Key": "1_10_2-15",
          "SourceString": "‥We won't give up yet!!",
          "LocalizedString": "‥We won't give up yet!!"
        },
        "DrawTime": 3.0,
        "Condition": {
          "Type": "EStoryRaceTalk_ConditionType::PlayerProgress",
          "ProgressRate": 0.81,
          "ProgressRateEnd": -1.0,
          "Rival": 0,
          "Advantage": 0.0
        }
      },
      "SRT_1_10_2-16": {
        "EpisodeID": 56,
        "CharacterID": "SAYUKI",
        "FaceImageNo": 0,
        "Message": {
          "TableId": "/Game/IND/StringTable/Story/Racetext/Storytype1/story_RT_1_10.story_RT_1_10",
          "Key": "1_10_2-16",
          "SourceString": "Mako, you're amazing after all!!",
          "LocalizedString": "Mako, you're amazing after all!!"
        },
        "DrawTime": 3.0,
        "Condition": {
          "Type": "EStoryRaceTalk_ConditionType::PlayerProgress",
          "ProgressRate": 0.83,
          "ProgressRateEnd": -1.0,
          "Rival": 0,
          "Advantage": 0.0
        }
      },
      "SRT_1_10_2-17": {
        "EpisodeID": 56,
        "CharacterID": "SAYUKI",
        "FaceImageNo": 0,
        "Message": {
          "TableId": "/Game/IND/StringTable/Story/Racetext/Storytype1/story_RT_1_10.story_RT_1_10",
          "Key": "1_10_2-17",
          "SourceString": "Let's keep this up‥\r\nand escape‥!!",
          "LocalizedString": "Let's keep this up‥\r\nand escape‥!!"
        },
        "DrawTime": 3.0,
        "Condition": {
          "Type": "EStoryRaceTalk_ConditionType::PlayerProgress",
          "ProgressRate": 0.85,
          "ProgressRateEnd": -1.0,
          "Rival": 0,
          "Advantage": 0.0
        }
      },
      "SRT_1_10_2-18": {
        "EpisodeID": 56,
        "CharacterID": "MAKO&SAYUKI",
        "FaceImageNo": 1,
        "Message": {
          "TableId": "/Game/IND/StringTable/Story/Racetext/Storytype1/story_RT_1_10.story_RT_1_10",
          "Key": "1_10_2-18",
          "SourceString": "Ugh!!",
          "LocalizedString": "Ugh!!"
        },
        "DrawTime": 3.0,
        "Condition": {
          "Type": "EStoryRaceTalk_ConditionType::AdvantageOver",
          "ProgressRate": 0.9,
          "ProgressRateEnd": 0.999,
          "Rival": 0,
          "Advantage": 0.5
        }
      },
      "SRT_1_10_3-01": {
        "EpisodeID": 57,
        "CharacterID": "EVO5MAN",
        "FaceImageNo": 0,
        "Message": {
          "TableId": "/Game/IND/StringTable/Story/Racetext/Storytype1/story_RT_1_10.story_RT_1_10",
          "Key": "1_10_3-01",
          "SourceString": "Hey!! Clear the way!!",
          "LocalizedString": "Hey!! Clear the way!!"
        },
        "DrawTime": 3.0,
        "Condition": {
          "Type": "EStoryRaceTalk_ConditionType::PlayerProgress",
          "ProgressRate": 0.275,
          "ProgressRateEnd": -1.0,
          "Rival": 0,
          "Advantage": 0.0
        }
      },
      "SRT_1_10_3-02": {
        "EpisodeID": 57,
        "CharacterID": "EVO6MAN",
        "FaceImageNo": 0,
        "Message": {
          "TableId": "/Game/IND/StringTable/Story/Racetext/Storytype1/story_RT_1_10.story_RT_1_10",
          "Key": "1_10_3-02",
          "SourceString": "Hey, hey‥\r\nDon't bully too much‥",
          "LocalizedString": "Hey, hey‥\r\nDon't bully too much‥"
        },
        "DrawTime": 3.0,
        "Condition": {
          "Type": "EStoryRaceTalk_ConditionType::PlayerProgress",
          "ProgressRate": 0.295,
          "ProgressRateEnd": -1.0,
          "Rival": 0,
          "Advantage": 0.0
        }
      },
      "SRT_1_10_3-03": {
        "EpisodeID": 57,
        "CharacterID": "EVO6MAN",
        "FaceImageNo": 0,
        "Message": {
          "TableId": "/Game/IND/StringTable/Story/Racetext/Storytype1/story_RT_1_10.story_RT_1_10",
          "Key": "1_10_3-03",
          "SourceString": "Let's enjoy it slowly,\r\nlet's take our time‥",
          "LocalizedString": "Let's enjoy it slowly,\r\nlet's take our time‥"
        },
        "DrawTime": 3.0,
        "Condition": {
          "Type": "EStoryRaceTalk_ConditionType::PlayerProgress",
          "ProgressRate": 0.315,
          "ProgressRateEnd": -1.0,
          "Rival": 0,
          "Advantage": 0.0
        }
      },
      "SRT_1_10_3-04": {
        "EpisodeID": 57,
        "CharacterID": "EVO5MAN",
        "FaceImageNo": 0,
        "Message": {
          "TableId": "/Game/IND/StringTable/Story/Racetext/Storytype1/story_RT_1_10.story_RT_1_10",
          "Key": "1_10_3-04",
          "SourceString": "Heh heh!! You're still as\r\nbad-tempered as ever‥ you",
          "LocalizedString": "Heh heh!! You're still as\r\nbad-tempered as ever‥ you"
        },
        "DrawTime": 3.0,
        "Condition": {
          "Type": "EStoryRaceTalk_ConditionType::PlayerProgress",
          "ProgressRate": 0.335,
          "ProgressRateEnd": -1.0,
          "Rival": 0,
          "Advantage": 0.0
        }
      },
      "SRT_1_10_3-05": {
        "EpisodeID": 57,
        "CharacterID": "EVO5MAN",
        "FaceImageNo": 0,
        "Message": {
          "TableId": "/Game/IND/StringTable/Story/Racetext/Storytype1/story_RT_1_10.story_RT_1_10",
          "Key": "1_10_3-05",
          "SourceString": "Hey, hey!! What's wrong,\r\nwhat's wrong!!",
          "LocalizedString": "Hey, hey!! What's wrong,\r\nwhat's wrong!!"
        },
        "DrawTime": 3.0,
        "Condition": {
          "Type": "EStoryRaceTalk_ConditionType::PlayerProgress",
          "ProgressRate": 0.375,
          "ProgressRateEnd": -1.0,
          "Rival": 0,
          "Advantage": 0.0
        }
      },
      "SRT_1_10_3-06": {
        "EpisodeID": 57,
        "CharacterID": "EVO5MAN",
        "FaceImageNo": 0,
        "Message": {
          "TableId": "/Game/IND/StringTable/Story/Racetext/Storytype1/story_RT_1_10.story_RT_1_10",
          "Key": "1_10_3-06",
          "SourceString": "If you're scared, you can\r\nstop running, you know？",
          "LocalizedString": "If you're scared, you can\r\nstop running, you know？"
        },
        "DrawTime": 3.0,
        "Condition": {
          "Type": "EStoryRaceTalk_ConditionType::PlayerProgress",
          "ProgressRate": 0.395,
          "ProgressRateEnd": -1.0,
          "Rival": 0,
          "Advantage": 0.0
        }
      },
      "SRT_1_10_3-07": {
        "EpisodeID": 57,
        "CharacterID": "EVO5MAN",
        "FaceImageNo": 0,
        "Message": {
          "TableId": "/Game/IND/StringTable/Story/Racetext/Storytype1/story_RT_1_10.story_RT_1_10",
          "Key": "1_10_3-07",
          "SourceString": "‥This guy, he's quite good",
          "LocalizedString": "‥This guy, he's quite good"
        },
        "DrawTime": 3.0,
        "Condition": {
          "Type": "EStoryRaceTalk_ConditionType::PlayerProgress",
          "ProgressRate": 0.6,
          "ProgressRateEnd": -1.0,
          "Rival": 0,
          "Advantage": 0.0
        }
      },
      "SRT_1_10_3-08": {
        "EpisodeID": 57,
        "CharacterID": "EVO6MAN",
        "FaceImageNo": 0,
        "Message": {
          "TableId": "/Game/IND/StringTable/Story/Racetext/Storytype1/story_RT_1_10.story_RT_1_10",
          "Key": "1_10_3-08",
          "SourceString": "‥They run like they don't\r\nfeel our pressure",
          "LocalizedString": "‥They run like they don't\r\nfeel our pressure"
        },
        "DrawTime": 3.0,
        "Condition": {
          "Type": "EStoryRaceTalk_ConditionType::PlayerProgress",
          "ProgressRate": 0.62,
          "ProgressRateEnd": -1.0,
          "Rival": 0,
          "Advantage": 0.0
        }
      },
      "SRT_1_10_3-09": {
        "EpisodeID": 57,
        "CharacterID": "EVO5MAN",
        "FaceImageNo": 0,
        "Message": {
          "TableId": "/Game/IND/StringTable/Story/Racetext/Storytype1/story_RT_1_10.story_RT_1_10",
          "Key": "1_10_3-09",
          "SourceString": "Tch‥ thinking about them\r\nmakes me feel unpleasant‥",
          "LocalizedString": "Tch‥ thinking about them\r\nmakes me feel unpleasant‥"
        },
        "DrawTime": 3.0,
        "Condition": {
          "Type": "EStoryRaceTalk_ConditionType::PlayerProgress",
          "ProgressRate": 0.64,
          "ProgressRateEnd": -1.0,
          "Rival": 0,
          "Advantage": 0.0
        }
      },
      "SRT_1_10_3-10": {
        "EpisodeID": 57,
        "CharacterID": "EVO6MAN",
        "FaceImageNo": 0,
        "Message": {
          "TableId": "/Game/IND/StringTable/Story/Racetext/Storytype1/story_RT_1_10.story_RT_1_10",
          "Key": "1_10_3-10",
          "SourceString": "‥Hey,\r\nI've come up with a good idea",
          "LocalizedString": "‥Hey,\r\nI've come up with a good idea"
        },
        "DrawTime": 3.0,
        "Condition": {
          "Type": "EStoryRaceTalk_ConditionType::PlayerProgress",
          "ProgressRate": 0.79,
          "ProgressRateEnd": -1.0,
          "Rival": 0,
          "Advantage": 0.0
        }
      },
      "SRT_1_10_3-11": {
        "EpisodeID": 57,
        "CharacterID": "EVO5MAN",
        "FaceImageNo": 0,
        "Message": {
          "TableId": "/Game/IND/StringTable/Story/Racetext/Storytype1/story_RT_1_10.story_RT_1_10",
          "Key": "1_10_3-11",
          "SourceString": "Oh‥？",
          "LocalizedString": "Oh‥？"
        },
        "DrawTime": 3.0,
        "Condition": {
          "Type": "EStoryRaceTalk_ConditionType::PlayerProgress",
          "ProgressRate": 0.81,
          "ProgressRateEnd": -1.0,
          "Rival": 0,
          "Advantage": 0.0
        }
      },
      "SRT_1_10_3-12": {
        "EpisodeID": 57,
        "CharacterID": "EVO6MAN",
        "FaceImageNo": 0,
        "Message": {
          "TableId": "/Game/IND/StringTable/Story/Racetext/Storytype1/story_RT_1_10.story_RT_1_10",
          "Key": "1_10_3-15",
          "SourceString": "Let's retreat once‥",
          "LocalizedString": "Let's retreat once‥"
        },
        "DrawTime": 3.0,
        "Condition": {
          "Type": "EStoryRaceTalk_ConditionType::PlayerProgress",
          "ProgressRate": 0.83,
          "ProgressRateEnd": -1.0,
          "Rival": 0,
          "Advantage": 0.0
        }
      },
      "SRT_1_10_3-13": {
        "EpisodeID": 57,
        "CharacterID": "EVO5MAN",
        "FaceImageNo": 0,
        "Message": {
          "TableId": "/Game/IND/StringTable/Story/Racetext/Storytype1/story_RT_1_10.story_RT_1_10",
          "Key": "1_10_3-16",
          "SourceString": "Heh‥ got it",
          "LocalizedString": "Heh‥ got it"
        },
        "DrawTime": 3.0,
        "Condition": {
          "Type": "EStoryRaceTalk_ConditionType::PlayerProgress",
          "ProgressRate": 0.85,
          "ProgressRateEnd": -1.0,
          "Rival": 0,
          "Advantage": 0.0
        }
      },
      "SRT_1_10_4-01": {
        "EpisodeID": 58,
        "CharacterID": "EVO6MAN",
        "FaceImageNo": 0,
        "Message": {
          "TableId": "/Game/IND/StringTable/Story/Racetext/Storytype1/story_RT_1_10.story_RT_1_10",
          "Key": "1_10_4-01",
          "SourceString": "Don't worry about the guys‥\r\njust let them watch the battle",
          "LocalizedString": "Don't worry about the guys‥\r\njust let them watch the battle"
        },
        "DrawTime": 3.0,
        "Condition": {
          "Type": "EStoryRaceTalk_ConditionType::PlayerProgress",
          "ProgressRate": 0.02,
          "ProgressRateEnd": -1.0,
          "Rival": 0,
          "Advantage": 0.0
        }
      },
      "SRT_1_10_4-02": {
        "EpisodeID": 58,
        "CharacterID": "EVO5MAN",
        "FaceImageNo": 0,
        "Message": {
          "TableId": "/Game/IND/StringTable/Story/Racetext/Storytype1/story_RT_1_10.story_RT_1_10",
          "Key": "1_10_4-02",
          "SourceString": "Heh heh‥ that's the plan",
          "LocalizedString": "Heh heh‥ that's the plan"
        },
        "DrawTime": 3.0,
        "Condition": {
          "Type": "EStoryRaceTalk_ConditionType::PlayerProgress",
          "ProgressRate": 0.04,
          "ProgressRateEnd": -1.0,
          "Rival": 0,
          "Advantage": 0.0
        }
      },
      "SRT_1_10_4-03": {
        "EpisodeID": 58,
        "CharacterID": "EVO6MAN",
        "FaceImageNo": 0,
        "Message": {
          "TableId": "/Game/IND/StringTable/Story/Racetext/Storytype1/story_RT_1_10.story_RT_1_10",
          "Key": "1_10_4-03",
          "SourceString": "However, I'll give you\r\na word of advice",
          "LocalizedString": "However, I'll give you\r\na word of advice"
        },
        "DrawTime": 3.0,
        "Condition": {
          "Type": "EStoryRaceTalk_ConditionType::PlayerProgress",
          "ProgressRate": 0.08,
          "ProgressRateEnd": -1.0,
          "Rival": 0,
          "Advantage": 0.0
        }
      },
      "SRT_1_10_4-04": {
        "EpisodeID": 58,
        "CharacterID": "EVO6MAN",
        "FaceImageNo": 0,
        "Message": {
          "TableId": "/Game/IND/StringTable/Story/Racetext/Storytype1/story_RT_1_10.story_RT_1_10",
          "Key": "1_10_4-04",
          "SourceString": "In mountain pass battles, you never\r\nknow what might happen, remember that",
          "LocalizedString": "In mountain pass battles, you never\r\nknow what might happen, remember that"
        },
        "DrawTime": 3.0,
        "Condition": {
          "Type": "EStoryRaceTalk_ConditionType::PlayerProgress",
          "ProgressRate": 0.1,
          "ProgressRateEnd": -1.0,
          "Rival": 0,
          "Advantage": 0.0
        }
      },
      "SRT_1_10_4-05": {
        "EpisodeID": 58,
        "CharacterID": "EVO6MAN",
        "FaceImageNo": 0,
        "Message": {
          "TableId": "/Game/IND/StringTable/Story/Racetext/Storytype1/story_RT_1_10.story_RT_1_10",
          "Key": "1_10_4-05",
          "SourceString": "Ohh, so fast, so fast \r\nThey're about to pass me",
          "LocalizedString": "Ohh, so fast, so fast \r\nThey're about to pass me"
        },
        "DrawTime": 3.0,
        "Condition": {
          "Type": "EStoryRaceTalk_ConditionType::PlayerProgress",
          "ProgressRate": 0.245,
          "ProgressRateEnd": -1.0,
          "Rival": 0,
          "Advantage": 0.0
        }
      },
      "SRT_1_10_4-06": {
        "EpisodeID": 58,
        "CharacterID": "EVO5MAN",
        "FaceImageNo": 0,
        "Message": {
          "TableId": "/Game/IND/StringTable/Story/Racetext/Storytype1/story_RT_1_10.story_RT_1_10",
          "Key": "1_10_4-06",
          "SourceString": "Hey, isn't it about time‥\r\nand having some fun",
          "LocalizedString": "Hey, isn't it about time‥\r\nand having some fun"
        },
        "DrawTime": 3.0,
        "Condition": {
          "Type": "EStoryRaceTalk_ConditionType::PlayerProgress",
          "ProgressRate": 0.275,
          "ProgressRateEnd": -1.0,
          "Rival": 0,
          "Advantage": 0.0
        }
      },
      "SRT_1_10_4-07": {
        "EpisodeID": 58,
        "CharacterID": "EVO6MAN",
        "FaceImageNo": 0,
        "Message": {
          "TableId": "/Game/IND/StringTable/Story/Racetext/Storytype1/story_RT_1_10.story_RT_1_10",
          "Key": "1_10_4-07",
          "SourceString": "Heh‥ such an impatient guy‥",
          "LocalizedString": "Heh‥ such an impatient guy‥"
        },
        "DrawTime": 3.0,
        "Condition": {
          "Type": "EStoryRaceTalk_ConditionType::PlayerProgress",
          "ProgressRate": 0.305,
          "ProgressRateEnd": -1.0,
          "Rival": 0,
          "Advantage": 0.0
        }
      },
      "SRT_1_10_4-08": {
        "EpisodeID": 58,
        "CharacterID": "EVO6MAN",
        "FaceImageNo": 0,
        "Message": {
          "TableId": "/Game/IND/StringTable/Story/Racetext/Storytype1/story_RT_1_10.story_RT_1_10",
          "Key": "1_10_4-08",
          "SourceString": "Hmph",
          "LocalizedString": "Hmph"
        },
        "DrawTime": 1.5,
        "Condition": {
          "Type": "EStoryRaceTalk_ConditionType::PlayerProgress",
          "ProgressRate": 0.335,
          "ProgressRateEnd": -1.0,
          "Rival": 0,
          "Advantage": 0.0
        }
      },
      "SRT_1_10_4-09": {
        "EpisodeID": 58,
        "CharacterID": "EVO5MAN",
        "FaceImageNo": 0,
        "Message": {
          "TableId": "/Game/IND/StringTable/Story/Racetext/Storytype1/story_RT_1_10.story_RT_1_10",
          "Key": "1_10_4-09",
          "SourceString": "Aghh‼ You, you hit my friend's car‼",
          "LocalizedString": "Aghh‼ You, you hit my friend's car‼"
        },
        "DrawTime": 3.0,
        "Condition": {
          "Type": "EStoryRaceTalk_ConditionType::PlayerProgress",
          "ProgressRate": 0.35,
          "ProgressRateEnd": -1.0,
          "Rival": 0,
          "Advantage": 0.0
        }
      },
      "SRT_1_10_4-10": {
        "EpisodeID": 58,
        "CharacterID": "EVO6MAN",
        "FaceImageNo": 0,
        "Message": {
          "TableId": "/Game/IND/StringTable/Story/Racetext/Storytype1/story_RT_1_10.story_RT_1_10",
          "Key": "1_10_4-10",
          "SourceString": "Uh‥ the car might be scratched...",
          "LocalizedString": "Uh‥ the car might be scratched..."
        },
        "DrawTime": 3.0,
        "Condition": {
          "Type": "EStoryRaceTalk_ConditionType::PlayerProgress",
          "ProgressRate": 0.38,
          "ProgressRateEnd": -1.0,
          "Rival": 0,
          "Advantage": 0.0
        }
      },
      "SRT_1_10_4-11": {
        "EpisodeID": 58,
        "CharacterID": "EVO5MAN",
        "FaceImageNo": 0,
        "Message": {
          "TableId": "/Game/IND/StringTable/Story/Racetext/Storytype1/story_RT_1_10.story_RT_1_10",
          "Key": "1_10_4-11",
          "SourceString": "Unforgivable‼\r\nI'll get even with you‼",
          "LocalizedString": "Unforgivable‼\r\nI'll get even with you‼"
        },
        "DrawTime": 3.0,
        "Condition": {
          "Type": "EStoryRaceTalk_ConditionType::PlayerProgress",
          "ProgressRate": 0.41,
          "ProgressRateEnd": -1.0,
          "Rival": 0,
          "Advantage": 0.0
        }
      },
      "SRT_1_10_4-12": {
        "EpisodeID": 58,
        "CharacterID": "EVO5MAN",
        "FaceImageNo": 0,
        "Message": {
          "TableId": "/Game/IND/StringTable/Story/Racetext/Storytype1/story_RT_1_10.story_RT_1_10",
          "Key": "1_10_4-12",
          "SourceString": "Hey, hey‼",
          "LocalizedString": "Hey, hey‼"
        },
        "DrawTime": 3.0,
        "Condition": {
          "Type": "EStoryRaceTalk_ConditionType::PlayerProgress",
          "ProgressRate": 0.49,
          "ProgressRateEnd": -1.0,
          "Rival": 0,
          "Advantage": 0.0
        }
      },
      "SRT_1_10_4-13": {
        "EpisodeID": 58,
        "CharacterID": "EVO6MAN",
        "FaceImageNo": 0,
        "Message": {
          "TableId": "/Game/IND/StringTable/Story/Racetext/Storytype1/story_RT_1_10.story_RT_1_10",
          "Key": "1_10_4-13",
          "SourceString": "Heh‥ it won't make any money,\r\nbut let's have a little fun",
          "LocalizedString": "Heh‥ it won't make any money,\r\nbut let's have a little fun"
        },
        "DrawTime": 3.0,
        "Condition": {
          "Type": "EStoryRaceTalk_ConditionType::PlayerProgress",
          "ProgressRate": 0.51,
          "ProgressRateEnd": -1.0,
          "Rival": 0,
          "Advantage": 0.0
        }
      },
      "SRT_1_10_4-14": {
        "EpisodeID": 58,
        "CharacterID": "EVO5MAN",
        "FaceImageNo": 0,
        "Message": {
          "TableId": "/Game/IND/StringTable/Story/Racetext/Storytype1/story_RT_1_10.story_RT_1_10",
          "Key": "1_10_4-14",
          "SourceString": "You idiot, you're hopeless!!",
          "LocalizedString": "You idiot, you're hopeless!!"
        },
        "DrawTime": 3.0,
        "Condition": {
          "Type": "EStoryRaceTalk_ConditionType::PlayerProgress",
          "ProgressRate": 0.61,
          "ProgressRateEnd": -1.0,
          "Rival": 0,
          "Advantage": 0.0
        }
      },
      "SRT_1_10_4-15": {
        "EpisodeID": 58,
        "CharacterID": "EVO5MAN",
        "FaceImageNo": 0,
        "Message": {
          "TableId": "/Game/IND/StringTable/Story/Racetext/Storytype1/story_RT_1_10.story_RT_1_10",
          "Key": "1_10_4-15",
          "SourceString": "Your face turns pale with fear!!",
          "LocalizedString": "Your face turns pale with fear!!"
        },
        "DrawTime": 3.0,
        "Condition": {
          "Type": "EStoryRaceTalk_ConditionType::PlayerProgress",
          "ProgressRate": 0.63,
          "ProgressRateEnd": -1.0,
          "Rival": 0,
          "Advantage": 0.0
        }
      },
      "SRT_1_10_4-16": {
        "EpisodeID": 58,
        "CharacterID": "EVO5MAN",
        "FaceImageNo": 1,
        "Message": {
          "TableId": "/Game/IND/StringTable/Story/Racetext/Storytype1/story_RT_1_10.story_RT_1_10",
          "Key": "1_10_4-16",
          "SourceString": "I can't shake them‥ why‥!?",
          "LocalizedString": "I can't shake them‥ why‥!?"
        },
        "DrawTime": 3.0,
        "Condition": {
          "Type": "EStoryRaceTalk_ConditionType::PlayerProgress",
          "ProgressRate": 0.69,
          "ProgressRateEnd": -1.0,
          "Rival": 0,
          "Advantage": 0.0
        }
      },
      "SRT_1_10_4-17": {
        "EpisodeID": 58,
        "CharacterID": "EVO5MAN",
        "FaceImageNo": 1,
        "Message": {
          "TableId": "/Game/IND/StringTable/Story/Racetext/Storytype1/story_RT_1_10.story_RT_1_10",
          "Key": "1_10_4-17",
          "SourceString": "Nooooo!!",
          "LocalizedString": "Nooooo!!"
        },
        "DrawTime": 3.0,
        "Condition": {
          "Type": "EStoryRaceTalk_ConditionType::AdvantageOver",
          "ProgressRate": 0.69,
          "ProgressRateEnd": 0.73,
          "Rival": 1,
          "Advantage": 0.1
        }
      },
      "SRT_1_10_4-18": {
        "EpisodeID": 58,
        "CharacterID": "EVO6MAN",
        "FaceImageNo": 1,
        "Message": {
          "TableId": "/Game/IND/StringTable/Story/Racetext/Storytype1/story_RT_1_10.story_RT_1_10",
          "Key": "1_10_4-18",
          "SourceString": "Hey‥ could it be‥",
          "LocalizedString": "Hey‥ could it be‥"
        },
        "DrawTime": 3.0,
        "Condition": {
          "Type": "EStoryRaceTalk_ConditionType::PlayerProgress",
          "ProgressRate": 0.85,
          "ProgressRateEnd": -1.0,
          "Rival": 0,
          "Advantage": 0.0
        }
      },
      "SRT_1_10_4-19": {
        "EpisodeID": 58,
        "CharacterID": "EVO5MAN",
        "FaceImageNo": 1,
        "Message": {
          "TableId": "/Game/IND/StringTable/Story/Racetext/Storytype1/story_RT_1_10.story_RT_1_10",
          "Key": "1_10_4-19",
          "SourceString": "No way!! Is he pursuing\r\nProject D‥ that guy!?",
          "LocalizedString": "No way!! Is he pursuing\r\nProject D‥ that guy!?"
        },
        "DrawTime": 3.0,
        "Condition": {
          "Type": "EStoryRaceTalk_ConditionType::PlayerProgress",
          "ProgressRate": 0.87,
          "ProgressRateEnd": -1.0,
          "Rival": 0,
          "Advantage": 0.0
        }
      },
      "SRT_1_10_4-20": {
        "EpisodeID": 58,
        "CharacterID": "EVO6MAN",
        "FaceImageNo": 1,
        "Message": {
          "TableId": "/Game/IND/StringTable/Story/Racetext/Storytype1/story_RT_1_10.story_RT_1_10",
          "Key": "1_10_4-20",
          "SourceString": "I'm done with anything\r\nrelated to them",
          "LocalizedString": "I'm done with anything\r\nrelated to them"
        },
        "DrawTime": 3.0,
        "Condition": {
          "Type": "EStoryRaceTalk_ConditionType::PlayerProgress",
          "ProgressRate": 0.89,
          "ProgressRateEnd": -1.0,
          "Rival": 0,
          "Advantage": 0.0
        }
      },
      "SRT_1_10_4-21": {
        "EpisodeID": 58,
        "CharacterID": "EVO6MAN",
        "FaceImageNo": 1,
        "Message": {
          "TableId": "/Game/IND/StringTable/Story/Racetext/Storytype1/story_RT_1_10.story_RT_1_10",
          "Key": "1_10_4-21",
          "SourceString": "Hey, let's go back‥",
          "LocalizedString": "Hey, let's go back‥"
        },
        "DrawTime": 3.0,
        "Condition": {
          "Type": "EStoryRaceTalk_ConditionType::PlayerProgress",
          "ProgressRate": 0.91,
          "ProgressRateEnd": -1.0,
          "Rival": 0,
          "Advantage": 0.0
        }
      },
      "SRT_1_10_4-22": {
        "EpisodeID": 58,
        "CharacterID": "EVO5MAN",
        "FaceImageNo": 1,
        "Message": {
          "TableId": "/Game/IND/StringTable/Story/Racetext/Storytype1/story_RT_1_10.story_RT_1_10",
          "Key": "1_10_4-22",
          "SourceString": "Tch‥ we're not getting anywhere",
          "LocalizedString": "Tch‥ we're not getting anywhere"
        },
        "DrawTime": 3.0,
        "Condition": {
          "Type": "EStoryRaceTalk_ConditionType::PlayerProgress",
          "ProgressRate": 0.93,
          "ProgressRateEnd": -1.0,
          "Rival": 0,
          "Advantage": 0.0
        }
      },
      "SRT_1_10_5-01": {
        "EpisodeID": 59,
        "CharacterID": "KYOKO",
        "FaceImageNo": 0,
        "Message": {
          "TableId": "/Game/IND/StringTable/Story/Racetext/Storytype1/story_RT_1_10.story_RT_1_10",
          "Key": "1_10_5-01",
          "SourceString": "I'm sorry‥\r\nfor asking the impossible‥",
          "LocalizedString": "I'm sorry‥\r\nfor asking the impossible‥"
        },
        "DrawTime": 3.0,
        "Condition": {
          "Type": "EStoryRaceTalk_ConditionType::PlayerProgress",
          "ProgressRate": 0.001,
          "ProgressRateEnd": -1.0,
          "Rival": 0,
          "Advantage": 0.0
        }
      },
      "SRT_1_10_5-02": {
        "EpisodeID": 59,
        "CharacterID": "KYOKO",
        "FaceImageNo": 0,
        "Message": {
          "TableId": "/Game/IND/StringTable/Story/Racetext/Storytype1/story_RT_1_10.story_RT_1_10",
          "Key": "1_10_5-02",
          "SourceString": "If you're as skilled as they\r\nsay‥ I might get fired up‥",
          "LocalizedString": "If you're as skilled as they\r\nsay‥ I might get fired up‥"
        },
        "DrawTime": 3.0,
        "Condition": {
          "Type": "EStoryRaceTalk_ConditionType::PlayerProgress",
          "ProgressRate": 0.02,
          "ProgressRateEnd": -1.0,
          "Rival": 0,
          "Advantage": 0.0
        }
      },
      "SRT_1_10_5-03": {
        "EpisodeID": 59,
        "CharacterID": "KYOKO",
        "FaceImageNo": 0,
        "Message": {
          "TableId": "/Game/IND/StringTable/Story/Racetext/Storytype1/story_RT_1_10.story_RT_1_10",
          "Key": "1_10_5-03",
          "SourceString": "As I thought‥ No‥",
          "LocalizedString": "As I thought‥ No‥"
        },
        "DrawTime": 3.0,
        "Condition": {
          "Type": "EStoryRaceTalk_ConditionType::PlayerProgress",
          "ProgressRate": 0.165,
          "ProgressRateEnd": -1.0,
          "Rival": 0,
          "Advantage": 0.0
        }
      },
      "SRT_1_10_5-04": {
        "EpisodeID": 59,
        "CharacterID": "KYOKO",
        "FaceImageNo": 0,
        "Message": {
          "TableId": "/Game/IND/StringTable/Story/Racetext/Storytype1/story_RT_1_10.story_RT_1_10",
          "Key": "1_10_5-04",
          "SourceString": "I can't get excited in\r\nthe car like usual‥",
          "LocalizedString": "I can't get excited in\r\nthe car like usual‥"
        },
        "DrawTime": 3.0,
        "Condition": {
          "Type": "EStoryRaceTalk_ConditionType::PlayerProgress",
          "ProgressRate": 0.185,
          "ProgressRateEnd": -1.0,
          "Rival": 0,
          "Advantage": 0.0
        }
      },
      "SRT_1_10_5-05": {
        "EpisodeID": 59,
        "CharacterID": "KYOKO",
        "FaceImageNo": 0,
        "Message": {
          "TableId": "/Game/IND/StringTable/Story/Racetext/Storytype1/story_RT_1_10.story_RT_1_10",
          "Key": "1_10_5-05",
          "SourceString": "No good‥\r\nI have to focus‥ concentrate‥",
          "LocalizedString": "No good‥\r\nI have to focus‥ concentrate‥"
        },
        "DrawTime": 3.0,
        "Condition": {
          "Type": "EStoryRaceTalk_ConditionType::PlayerProgress",
          "ProgressRate": 0.24,
          "ProgressRateEnd": -1.0,
          "Rival": 0,
          "Advantage": 0.0
        }
      },
      "SRT_1_10_5-06": {
        "EpisodeID": 59,
        "CharacterID": "KYOKO",
        "FaceImageNo": 0,
        "Message": {
          "TableId": "/Game/IND/StringTable/Story/Racetext/Storytype1/story_RT_1_10.story_RT_1_10",
          "Key": "1_10_5-06",
          "SourceString": "I can do it‥ I might\r\npass in the next one‥",
          "LocalizedString": "I can do it‥ I might\r\npass in the next one‥"
        },
        "DrawTime": 3.0,
        "Condition": {
          "Type": "EStoryRaceTalk_ConditionType::PlayerProgress",
          "ProgressRate": 0.305,
          "ProgressRateEnd": -1.0,
          "Rival": 0,
          "Advantage": 0.0
        }
      },
      "SRT_1_10_5-07": {
        "EpisodeID": 59,
        "CharacterID": "KYOKO",
        "FaceImageNo": 0,
        "Message": {
          "TableId": "/Game/IND/StringTable/Story/Racetext/Storytype1/story_RT_1_10.story_RT_1_10",
          "Key": "1_10_5-07",
          "SourceString": "Ugh‥!!",
          "LocalizedString": "Ugh‥!!"
        },
        "DrawTime": 1.5,
        "Condition": {
          "Type": "EStoryRaceTalk_ConditionType::PlayerProgress",
          "ProgressRate": 0.35,
          "ProgressRateEnd": -1.0,
          "Rival": 0,
          "Advantage": 2.0
        }
      },
      "SRT_1_10_5-08": {
        "EpisodeID": 59,
        "CharacterID": "KYOKO",
        "FaceImageNo": 0,
        "Message": {
          "TableId": "/Game/IND/StringTable/Story/Racetext/Storytype1/story_RT_1_10.story_RT_1_10",
          "Key": "1_10_5-08",
          "SourceString": "Why‥ such a mistake‥",
          "LocalizedString": "Why‥ such a mistake‥"
        },
        "DrawTime": 3.0,
        "Condition": {
          "Type": "EStoryRaceTalk_ConditionType::PlayerProgress",
          "ProgressRate": 0.365,
          "ProgressRateEnd": -1.0,
          "Rival": 0,
          "Advantage": 0.0
        }
      },
      "SRT_1_10_5-09": {
        "EpisodeID": 59,
        "CharacterID": "KYOKO",
        "FaceImageNo": 0,
        "Message": {
          "TableId": "/Game/IND/StringTable/Story/Racetext/Storytype1/story_RT_1_10.story_RT_1_10",
          "Key": "1_10_5-09",
          "SourceString": "I won't hesitate anymore!!",
          "LocalizedString": "I won't hesitate anymore!!"
        },
        "DrawTime": 3.0,
        "Condition": {
          "Type": "EStoryRaceTalk_ConditionType::PlayerProgress",
          "ProgressRate": 0.503,
          "ProgressRateEnd": -1.0,
          "Rival": 0,
          "Advantage": 0.0
        }
      },
      "SRT_1_10_5-10": {
        "EpisodeID": 59,
        "CharacterID": "KYOKO",
        "FaceImageNo": 0,
        "Message": {
          "TableId": "/Game/IND/StringTable/Story/Racetext/Storytype1/story_RT_1_10.story_RT_1_10",
          "Key": "1_10_5-10",
          "SourceString": "As I thought‥\r\nI want to be in the lead!!",
          "LocalizedString": "As I thought‥\r\nI want to be in the lead!!"
        },
        "DrawTime": 3.0,
        "Condition": {
          "Type": "EStoryRaceTalk_ConditionType::AdvantageLess",
          "ProgressRate": 0.71,
          "ProgressRateEnd": 0.85,
          "Rival": 0,
          "Advantage": 5.0
        }
      },
      "SRT_1_10_5-11": {
        "EpisodeID": 59,
        "CharacterID": "KYOKO",
        "FaceImageNo": 0,
        "Message": {
          "TableId": "/Game/IND/StringTable/Story/Racetext/Storytype1/story_RT_1_10.story_RT_1_10",
          "Key": "1_10_5-11",
          "SourceString": "Just like this‥ all the\r\nway to the finish line!!",
          "LocalizedString": "Just like this‥ all the\r\nway to the finish line!!"
        },
        "DrawTime": 3.0,
        "Condition": {
          "Type": "EStoryRaceTalk_ConditionType::PlayerProgress",
          "ProgressRate": 0.865,
          "ProgressRateEnd": -1.0,
          "Rival": 0,
          "Advantage": 0.0
        }
      },
      "SRT_1_10_5-12": {
        "EpisodeID": 59,
        "CharacterID": "KYOKO",
        "FaceImageNo": 1,
        "Message": {
          "TableId": "/Game/IND/StringTable/Story/Racetext/Storytype1/story_RT_1_10.story_RT_1_10",
          "Key": "1_10_5-12",
          "SourceString": "‥!!",
          "LocalizedString": "‥!!"
        },
        "DrawTime": 3.0,
        "Condition": {
          "Type": "EStoryRaceTalk_ConditionType::AdvantageOver",
          "ProgressRate": 0.9,
          "ProgressRateEnd": 0.999,
          "Rival": 0,
          "Advantage": 0.5
        }
      }
    }
  }
]